enamlx/__init__.py
enamlx/core/__init__.py
enamlx/core/block.py
enamlx/core/looper.py
enamlx/core/middleware.py
enamlx/qt/__init__.py
enamlx/qt/qt_abstract_item.py
enamlx/qt/qt_abstract_item_view.py
enamlx/qt/qt_double_spin_box.py
enamlx/qt/qt_factories.py
enamlx/qt/qt_graphics_view.py
enamlx/qt/qt_key_event.py
enamlx/qt/qt_plot_area.py
enamlx/qt/qt_table_view.py
enamlx/qt/qt_tree_view.py
enamlx/widgets/__init__.py
enamlx/widgets/abstract_item.py
enamlx/widgets/abstract_item_view.py
enamlx/widgets/api.py
enamlx/widgets/double_spin_box.py
enamlx/widgets/graphics_view.py
enamlx/widgets/key_event.py
enamlx/widgets/plot_area.py
enamlx/widgets/table_view.py
enamlx/widgets/tree_view.py
enamlx-0.6.3.dist-info/LICENSE
enamlx-0.6.3.dist-info/METADATA
enamlx-0.6.3.dist-info/WHEEL
enamlx-0.6.3.dist-info/top_level.txt
enamlx-0.6.3.dist-info/RECORD
