Metadata-Version: 2.1
Name: enamlx
Version: 0.6.3
Summary: Additional Qt Widgets for Enaml
Home-page: https://github.com/frmdstryr/enamlx
Author: frmdstryr
Author-email: frmdstryr@gmail.com
Keywords: enaml,qt,tree,table,widgets
Classifier: Development Status :: 3 - Alpha
Classifier: Intended Audience :: Developers
Classifier: Operating System :: OS Independent
Classifier: License :: OSI Approved :: MIT License
Classifier: Programming Language :: Python
Classifier: Programming Language :: Python :: 3
Classifier: Topic :: Software Development :: Libraries :: Python Modules
License-File: LICENSE
Requires-Dist: enaml
